Workbook

Sheet INPUTS
A1: parameter | B1: value | C1: unit | D1: definition (FR/EN) | E1: source / justification | F1: editable?
A2: ASSET_SENSITIVE_2024_mEUR | B2: 652512 | C2: mEUR | D2: Actifs sensibles au taux (IR-sensitive assets) | E2: Bilan consolidé 31/12/2024 - tableau sensitivités (flag Y) | F2: NO
A3: LIAB_SENSITIVE_2024_mEUR | B3: 702815 | C3: mEUR | D3: Passifs sensibles au taux (IR-sensitive liabilities) | E3: Bilan consolidé 31/12/2024 - tableau sensitivités (flag Y) | F3: NO
A4: NET_BUCKET_LT1Y_mEUR | B4: -95348 | C4: mEUR | D4: Net IR-sensitive exposure <1y (Assets-Liab) | E4: Buckets Actif/Passif (flag Y), 2024 | F4: NO
A5: NET_BUCKET_1_5Y_mEUR | B5: 121299 | C5: mEUR | D5: Net IR-sensitive exposure 1-5y (Assets-Liab) | E5: Buckets Actif/Passif (flag Y), 2024 | F5: NO
A6: NET_BUCKET_GT5Y_mEUR | B6: 333926 | C6: mEUR | D6: Net IR-sensitive exposure >5y (Assets-Liab) | E6: Buckets Actif/Passif (flag Y), 2024 | F6: NO
A7: OBS_DELTA_EVE_+100BP_mEUR | B7: -24443.4 | C7: mEUR | D7: Observed ΔEVE for +100bp (proxy) | E7: Table sensitivités 2024: (ΔActif - ΔPassif) pour +100bp | F7: NO
A8: PV01_LT1Y_mEUR_per_bp | B8: 3.1878541 | C8: mEUR/bp | D8: Bucket PV01 allocation <1y | E8: Allocated from net buckets + durations, scaled to match observed PV01 total | F8: NO
A9: PV01_1_5Y_mEUR_per_bp | B9: -24.332981 | C9: mEUR/bp | D9: Bucket PV01 allocation 1-5y | E9: Allocated from net buckets + durations, scaled to match observed PV01 total | F9: NO
A10: PV01_GT5Y_mEUR_per_bp | B10: -223.28887 | C10: mEUR/bp | D10: Bucket PV01 allocation >5y | E10: Allocated from net buckets + durations, scaled to match observed PV01 total | F10: NO
A11: GAP_LT1Y_mEUR | B11: -95348 | C11: mEUR | D11: Repricing gap <1y for NII 12m proxy | E11: NET_BUCKET_LT1Y_mEUR | F11: NO
A12: MID_SHOCK_FORMULA | B12: =(short+long)/2 + curv/2 | C12: bp | D12: Definition of mid shock from (short,long,curv) | E12: Model convention used in Phase 3/4 | F12: NO
A13: DIVIDEND_PLANNED_mEUR | B13: 0 | C13: mEUR | D13: Dividend planned (Dividende prévu) | E13: RST objective: 'dividende holding = 0' => 0 | F13: YES
A14: CASH0_mEUR | B14: 4172 | C14: mEUR | D14: Cash & cash equivalents (Trésorerie) | E14: DEU 2024 - tableau flux / note trésorerie (Groupe) | F14: YES
A15: CREDIT_LINE_mEUR | B15: 3000 | C15: mEUR | D15: Committed credit line (Ligne de crédit confirmée) | E15: DEU 2024 - liquidité (proxy si détail non public) | F15: YES
A16: CREDIT_LINE_HAIRCUT | B16: 0.8 | C16: ratio | D16: Haircut applied to credit line availability | E16: Prudent assumption | F16: YES
A17: BUFFER_LIQ_mEUR | B17: 2000 | C17: mEUR | D17: Liquidity buffer (seuil de trésorerie) | E17: DEU liquidité + convention interne (proxy) | F17: YES
A18: TAX_RATE | B18: 0.25 | C18: ratio | D18: Effective tax rate (taux d'impôt) used for ΔNII→ΔRN | E18: Proxy (à affiner via note impôts) | F18: YES
A19: wC | B19: 1 | C19: ratio | D19: Weight applying ΔNII to holding cash/RN (poids consolidation) | E19: Proxy: 1 = full pass-through | F19: YES
A20: K_EVE_BUFFER | B20: 0.02 | C20: ratio | D20: Cash buffer trigger per € economic loss (k_eve) | E20: Proxy: 2% of max(0,-ΔEVE) | F20: YES
A21: CET1_RATIO0 | B21: 0.178 | C21: ratio | D21: CET1 ratio baseline (LBP) | E21: DEU 2024 LBP - Ratios prudentiels (CET1 17.8%) | F21: YES
A22: CET1_FLOOR_MDA | B22: 0.094 | C22: ratio | D22: CET1 floor (SREP CET1 requirement) | E22: DEU 2024 LBP - Exigence SREP CET1 9.4% | F22: YES
A23: CET1_TARGET | B23: 0.13 | C23: ratio | D23: CET1 internal target (management buffer) | E23: Proxy (à remplacer par cible interne si dispo) | F23: YES
A24: dCET1_per_mEUR_EVE | B24: 1e-06 | C24: ratio/mEUR | D24: Sensitivity CET1 to ΔEVE (pass-through) | E24: Proxy; set via RWA & OCI haircut / hedges | F24: YES
... A32: dDistributable_per_mEUR_RN | B32: 1 | C32: ratio | D32: Pass-through RN to distributable reserves | E32: Simplified proxy | F32: YES

Sheet SENSITIVITY_2024_Y
A1: bucket | B1: asset_mEUR | C1: liability_mEUR | D1: net_mEUR | E1: Dur_proxy | F1: PV01_raw_mEUR/bp | G1: scale_k | H1: PV01_adj_mEUR/bp | I1: comment
A2: lt_1y | B2: 165883 | C2: 261231 | D2: -95348 | E2: 0.5 | F2: 4.7674 | G2: 0.66867771 | H2: 3.1878541 | I2: Allocation PV01 by bucket scaled to match observed ΔEVE(+100bp)
A3: y1_5y | B3: 146915 | C3: 25616 | D3: 121299 | E3: 3 | F3: -36.3897 | G3: 0.66867771 | H3: -24.332981 | I3: Allocation PV01 by bucket scaled to match observed ΔEVE(+100bp)
A4: gt_5y | B4: 383114 | C4: 49188 | D4: 333926 | E4: 10 | F4: -333.926 | G4: 0.66867771 | H4: -223.28887 | I4: Allocation PV01 by bucket scaled to match observed ΔEVE(+100bp)

Sheet FRONTIER_POINTS
A1: dr_short_bp | B1: dr_long_bp | C1: curv_bp | D1: dr_mid_bp | E1: theta_L2_bp | F1: delta_EVE_mEUR | G1: delta_NII_12m_mEUR | H1: div_max_cash_mEUR | I1: fail_cash | J1: CET1_ratio | K1: fail_CET1_target | L1: fail_CET1_floor | M1: SII_ratio | N1: fail_SII_target | O1: fail_SII_floor | P1: RN_mEUR | Q1: Distributable_mEUR | R1: fail_legal | S1: NoDividend_target | T1: NoDividend_floor
A2: -300 | B2: -300 | C2: -200 | D2: =(A2+B2)/2 + C2/2 | E2: =SQRT(A2^2+B2^2+C2^2) | F2: =INPUTS!$B$8*A2+INPUTS!$B$9*D2+INPUTS!$B$10*B2 | G2: =INPUTS!$B$11*A2/10000 | H2: =MAX(0, (INPUTS!$B$14+INPUTS!$B$16*INPUTS!$B$15) + (1-INPUTS!$B$18)*INPUTS!$B$19*G2 - INPUTS!$B$17 - INPUTS!$B$20*MAX(0, -F2)) | I2: =IF(INPUTS!$B$13=0, H2<=0, H2<INPUTS!$B$13) | J2: =INPUTS!$B$21 + INPUTS!$B$24*F2 + INPUTS!$B$25*G2 | K2: =J2<INPUTS!$B$23 | L2: =J2<INPUTS!$B$22 | M2: =INPUTS!$B$26 + INPUTS!$B$29*F2 | N2: =M2<INPUTS!$B$28 | O2: =M2<INPUTS!$B$27 | P2: =INPUTS!$B$30 + (1-INPUTS!$B$18)*INPUTS!$B$19*G2 | Q2: =INPUTS!$B$31 + INPUTS!$B$32*P2 | R2: =IF(INPUTS!$B$13=0, Q2<=0, Q2<INPUTS!$B$13) | S2: =OR(I2,K2,N2,R2) | T2: =OR(I2,L2,O2,R2)
A3: -300 | B3: -300 | C3: -175 | D3: =(A3+B3)/2 + C3/2 | E3: =SQRT(A3^2+B3^2+C3^2) | F3: =INPUTS!$B$8*A3+INPUTS!$B$9*D3+INPUTS!$B$10*B3 | G3: =INPUTS!$B$11*A3/10000 | H3: =MAX(0, (INPUTS!$B$14+INPUTS!$B$16*INPUTS!$B$15) + (1-INPUTS!$B$18)*INPUTS!$B$19*G3 - INPUTS!$B$17 - INPUTS!$B$20*MAX(0, -F3)) | I3: =IF(INPUTS!$B$13=0, H3<=0, H3<INPUTS!$B$13) | J3: =INPUTS!$B$21 + INPUTS!$B$24*F3 + INPUTS!$B$25*G3 | K3: =J3<INPUTS!$B$23 | L3: =J3<INPUTS!$B$22 | M3: =INPUTS!$B$26 + INPUTS!$B$29*F3 | N3: =M3<INPUTS!$B$28 | O3: =M3<INPUTS!$B$27 | P3: =INPUTS!$B$30 + (1-INPUTS!$B$18)*INPUTS!$B$19*G3 | Q3: =INPUTS!$B$31 + INPUTS!$B$32*P3 | R3: =IF(INPUTS!$B$13=0, Q3<=0, Q3<INPUTS!$B$13) | S3: =OR(I3,K3,N3,R3) | T3: =OR(I3,L3,O3,R3)
A4: -300 | B4: -300 | C4: -150 | D4: =(A4+B4)/2 + C4/2 | E4: =SQRT(A4^2+B4^2+C4^2) | F4: =INPUTS!$B$8*A4+INPUTS!$B$9*D4+INPUTS!$B$10*B4 | G4: =INPUTS!$B$11*A4/10000 | H4: =MAX(0, (INPUTS!$B$14+INPUTS!$B$16*INPUTS!$B$15) + (1-INPUTS!$B$18)*INPUTS!$B$19*G4 - INPUTS!$B$17 - INPUTS!$B$20*MAX(0, -F4)) | I4: =IF(INPUTS!$B$13=0, H4<=0, H4<INPUTS!$B$13) | J4: =INPUTS!$B$21 + INPUTS!$B$24*F4 + INPUTS!$B$25*G4 | K4: =J4<INPUTS!$B$23 | L4: =J4<INPUTS!$B$22 | M4: =INPUTS!$B$26 + INPUTS!$B$29*F4 | N4: =M4<INPUTS!$B$28 | O4: =M4<INPUTS!$B$27 | P4: =INPUTS!$B$30 + (1-INPUTS!$B$18)*INPUTS!$B$19*G4 | Q4: =INPUTS!$B$31 + INPUTS!$B$32*P4 | R4: =IF(INPUTS!$B$13=0, Q4<=0, Q4<INPUTS!$B$13) | S4: =OR(I4,K4,N4,R4) | T4: =OR(I4,L4,O4,R4)
A5: -300 | B5: -300 | C5: -125 | D5: =(A5+B5)/2 + C5/2 | E5: =SQRT(A5^2+B5^2+C5^2) | F5: =INPUTS!$B$8*A5+INPUTS!$B$9*D5+INPUTS!$B$10*B5 | G5: =INPUTS!$B$11*A5/10000 | H5: =MAX(0, (INPUTS!$B$14+INPUTS!$B$16*INPUTS!$B$15) + (1-INPUTS!$B$18)*INPUTS!$B$19*G5 - INPUTS!$B$17 - INPUTS!$B$20*MAX(0, -F5)) | I5: =IF(INPUTS!$B$13=0, H5<=0, H5<INPUTS!$B$13) | J5: =INPUTS!$B$21 + INPUTS!$B$24*F5 + INPUTS!$B$25*G5 | K5: =J5<INPUTS!$B$23 | L5: =J5<INPUTS!$B$22 | M5: =INPUTS!$B$26 + INPUTS!$B$29*F5 | N5: =M5<INPUTS!$B$28 | O5: =M5<INPUTS!$B$27 | P5: =INPUTS!$B$30 + (1-INPUTS!$B$18)*INPUTS!$B$19*G5 | Q5: =INPUTS!$B$31 + INPUTS!$B$32*P5 | R5: =IF(INPUTS!$B$13=0, Q5<=0, Q5<INPUTS!$B$13) | S5: =OR(I5,K5,N5,R5) | T5: =OR(I5,L5,O5,R5)
A6: -300 | B6: -300 | C6: -100 | D6: =(A6+B6)/2 + C6/2 | E6: =SQRT(A6^2+B6^2+C6^2) | F6: =INPUTS!$B$8*A6+INPUTS!$B$9*D6+INPUTS!$B$10*B6 | G6: =INPUTS!$B$11*A6/10000 | H6: =MAX(0, (INPUTS!$B$14+INPUTS!$B$16*INPUTS!$B$15) + (1-INPUTS!$B$18)*INPUTS!$B$19*G6 - INPUTS!$B$17 - INPUTS!$B$20*MAX(0, -F6)) | I6: =IF(INPUTS!$B$13=0, H6<=0, H6<INPUTS!$B$13) | J6: =INPUTS!$B$21 + INPUTS!$B$24*F6 + INPUTS!$B$25*G6 | K6: =J6<INPUTS!$B$23 | L6: =J6<INPUTS!$B$22 | M6: =INPUTS!$B$26 + INPUTS!$B$29*F6 | N6: =M6<INPUTS!$B$28 | O6: =M6<INPUTS!$B$27 | P6: =INPUTS!$B$30 + (1-INPUTS!$B$18)*INPUTS!$B$19*G6 | Q6: =INPUTS!$B$31 + INPUTS!$B$32*P6 | R6: =IF(INPUTS!$B$13=0, Q6<=0, Q6<INPUTS!$B$13) | S6: =OR(I6,K6,N6,R6) | T6: =OR(I6,L6,O6,R6)
A7: -300 | B7: -300 | C7: -75 | D7: =(A7+B7)/2 + C7/2 | E7: =SQRT(A7^2+B7^2+C7^2) | F7: =INPUTS!$B$8*A7+INPUTS!$B$9*D7+INPUTS!$B$10*B7 | G7: =INPUTS!$B$11*A7/10000 | H7: =MAX(0, (INPUTS!$B$14+INPUTS!$B$16*INPUTS!$B$15) + (1-INPUTS!$B$18)*INPUTS!$B$19*G7 - INPUTS!$B$17 - INPUTS!$B$20*MAX(0, -F7)) | I7: =IF(INPUTS!$B$13=0, H7<=0, H7<INPUTS!$B$13) | J7: =INPUTS!$B$21 + INPUTS!$B$24*F7 + INPUTS!$B$25*G7 | K7: =J7<INPUTS!$B$23 | L7: =J7<INPUTS!$B$22 | M7: =INPUTS!$B$26 + INPUTS!$B$29*F7 | N7: =M7<INPUTS!$B$28 | O7: =M7<INPUTS!$B$27 | P7: =INPUTS!$B$30 + (1-INPUTS!$B$18)*INPUTS!$B$19*G7 | Q7: =INPUTS!$B$31 + INPUTS!$B$32*P7 | R7: =IF(INPUTS!$B$13=0, Q7<=0, Q7<INPUTS!$B$13) | S7: =OR(I7,K7,N7,R7) | T7: =OR(I7,L7,O7,R7)
A8: -300 | B8: -300 | C8: -50 | D8: =(A8+B8)/2 + C8/2 | E8: =SQRT(A8^2+B8^2+C8^2) | F8: =INPUTS!$B$8*A8+INPUTS!$B$9*D8+INPUTS!$B$10*B8 | G8: =INPUTS!$B$11*A8/10000 | H8: =MAX(0, (INPUTS!$B$14+INPUTS!$B$16*INPUTS!$B$15) + (1-INPUTS!$B$18)*INPUTS!$B$19*G8 - INPUTS!$B$17 - INPUTS!$B$20*MAX(0, -F8)) | I8: =IF(INPUTS!$B$13=0, H8<=0, H8<INPUTS!$B$13) | J8: =INPUTS!$B$21 + INPUTS!$B$24*F8 + INPUTS!$B$25*G8 | K8: =J8<INPUTS!$B$23 | L8: =J8<INPUTS!$B$22 | M8: =INPUTS!$B$26 + INPUTS!$B$29*F8 | N8: =M8<INPUTS!$B$28 | O8: =M8<INPUTS!$B$27 | P8: =INPUTS!$B$30 + (1-INPUTS!$B$18)*INPUTS!$B$19*G8 | Q8: =INPUTS!$B$31 + INPUTS!$B$32*P8 | R8: =IF(INPUTS!$B$13=0, Q8<=0, Q8<INPUTS!$B$13) | S8: =OR(I8,K8,N8,R8) | T8: =OR(I8,L8,O8,R8)
A9: -300 | B9: -300 | C9: -25 | D9: =(A9+B9)/2 + C9/2 | E9: =SQRT(A9^2+B9^2+C9^2) | F9: =INPUTS!$B$8*A9+INPUTS!$B$9*D9+INPUTS!$B$10*B9 | G9: =INPUTS!$B$11*A9/10000 | H9: =MAX(0, (INPUTS!$B$14+INPUTS!$B$16*INPUTS!$B$15) + (1-INPUTS!$B$18)*INPUTS!$B$19*G9 - INPUTS!$B$17 - INPUTS!$B$20*MAX(0, -F9)) | I9: =IF(INPUTS!$B$13=0, H9<=0, H9<INPUTS!$B$13) | J9: =INPUTS!$B$21 + INPUTS!$B$24*F9 + INPUTS!$B$25*G9 | K9: =J9<INPUTS!$B$23 | L9: =J9<INPUTS!$B$22 | M9: =INPUTS!$B$26 + INPUTS!$B$29*F9 | N9: =M9<INPUTS!$B$28 | O9: =M9<INPUTS!$B$27 | P9: =INPUTS!$B$30 + (1-INPUTS!$B$18)*INPUTS!$B$19*G9 | Q9: =INPUTS!$B$31 + INPUTS!$B$32*P9 | R9: =IF(INPUTS!$B$13=0, Q9<=0, Q9<INPUTS!$B$13) | S9: =OR(I9,K9,N9,R9) | T9: =OR(I9,L9,O9,R9)
A10: -300 | B10: -300 | C10: 0 | D10: =(A10+B10)/2 + C10/2 | E10: =SQRT(A10^2+B10^2+C10^2) | F10: =INPUTS!$B$8*A10+INPUTS!$B$9*D10+INPUTS!$B$10*B10 | G10: =INPUTS!$B$11*A10/10000 | H10: =MAX(0, (INPUTS!$B$14+INPUTS!$B$16*INPUTS!$B$15) + (1-INPUTS!$B$18)*INPUTS!$B$19*G10 - INPUTS!$B$17 - INPUTS!$B$20*MAX(0, -F10)) | I10: =IF(INPUTS!$B$13=0, H10<=0, H10<INPUTS!$B$13) | J10: =INPUTS!$B$21 + INPUTS!$B$24*F10 + INPUTS!$B$25*G10 | K10: =J10<INPUTS!$B$23 | L10: =J10<INPUTS!$B$22 | M10: =INPUTS!$B$26 + INPUTS!$B$29*F10 | N10: =M10<INPUTS!$B$28 | O10: =M10<INPUTS!$B$27 | P10: =INPUTS!$B$30 + (1-INPUTS!$B$18)*INPUTS!$B$19*G10 | Q10: =INPUTS!$B$31 + INPUTS!$B$32*P10 | R10: =IF(INPUTS!$B$13=0, Q10<=0, Q10<INPUTS!$B$13) | S10: =OR(I10,K10,N10,R10) | T10: =OR(I10,L10,O10,R10)
A11: -300 | B11: -300 | C11: 25 | D11: =(A11+B11)/2 + C11/2 | E11: =SQRT(A11^2+B11^2+C11^2) | F11: =INPUTS!$B$8*A11+INPUTS!$B$9*D11+INPUTS!$B$10*B11 | G11: =INPUTS!$B$11*A11/10000 | H11: =MAX(0, (INPUTS!$B$14+INPUTS!$B$16*INPUTS!$B$15) + (1-INPUTS!$B$18)*INPUTS!$B$19*G11 - INPUTS!$B$17 - INPUTS!$B$20*MAX(0, -F11)) | I11: =IF(INPUTS!$B$13=0, H11<=0, H11<INPUTS!$B$13) | J11: =INPUTS!$B$21 + INPUTS!$B$24*F11 + INPUTS!$B$25*G11 | K11: =J11<INPUTS!$B$23 | L11: =J11<INPUTS!$B$22 | M11: =INPUTS!$B$26 + INPUTS!$B$29*F11 | N11: =M11<INPUTS!$B$28 | O11: =M11<INPUTS!$B$27 | P11: =INPUTS!$B$30 + (1-INPUTS!$B$18)*INPUTS!$B$19*G11 | Q11: =INPUTS!$B$31 + INPUTS!$B$32*P11 | R11: =IF(INPUTS!$B$13=0, Q11<=0, Q11<INPUTS!$B$13) | S11: =OR(I11,K11,N11,R11) | T11: =OR(I11,L11,O11,R11)
A12: -300 | B12: -300 | C12: 50 | D12: =(A12+B12)/2 + C12/2 | E12: =SQRT(A12^2+B12^2+C12^2) | F12: =INPUTS!$B$8*A12+INPUTS!$B$9*D12+INPUTS!$B$10*B12 | G12: =INPUTS!$B$11*A12/10000 | H12: =MAX(0, (INPUTS!$B$14+INPUTS!$B$16*INPUTS!$B$15) + (1-INPUTS!$B$18)*INPUTS!$B$19*G12 - INPUTS!$B$17 - INPUTS!$B$20*MAX(0, -F12)) | I12: =IF(INPUTS!$B$13=0, H12<=0, H12<INPUTS!$B$13) | J12: =INPUTS!$B$21 + INPUTS!$B$24*F12 + INPUTS!$B$25*G12 | K12: =J12<INPUTS!$B$23 | L12: =J12<INPUTS!$B$22 | M12: =INPUTS!$B$26 + INPUTS!$B$29*F12 | N12: =M12<INPUTS!$B$28 | O12: =M12<INPUTS!$B$27 | P12: =INPUTS!$B$30 + (1-INPUTS!$B$18)*INPUTS!$B$19*G12 | Q12: =INPUTS!$B$31 + INPUTS!$B$32*P12 | R12: =IF(INPUTS!$B$13=0, Q12<=0, Q12<INPUTS!$B$13) | S12: =OR(I12,K12,N12,R12) | T12: =OR(I12,L12,O12,R12)
A13: -300 | B13: -300 | C13: 75 | D13: =(A13+B13)/2 + C13/2 | E13: =SQRT(A13^2+B13^2+C13^2) | F13: =INPUTS!$B$8*A13+INPUTS!$B$9*D13+INPUTS!$B$10*B13 | G13: =INPUTS!$B$11*A13/10000 | H13: =MAX(0, (INPUTS!$B$14+INPUTS!$B$16*INPUTS!$B$15) + (1-INPUTS!$B$18)*INPUTS!$B$19*G13 - INPUTS!$B$17 - INPUTS!$B$20*MAX(0, -F13)) | I13: =IF(INPUTS!$B$13=0, H13<=0, H13<INPUTS!$B$13) | J13: =INPUTS!$B$21 + INPUTS!$B$24*F13 + INPUTS!$B$25*G13 | K13: =J13<INPUTS!$B$23 | L13: =J13<INPUTS!$B$22 | M13: =INPUTS!$B$26 + INPUTS!$B$29*F13 | N13: =M13<INPUTS!$B$28 | O13: =M13<INPUTS!$B$27 | P13: =INPUTS!$B$30 + (1-INPUTS!$B$18)*INPUTS!$B$19*G13 | Q13: =INPUTS!$B$31 + INPUTS!$B$32*P13 | R13: =IF(INPUTS!$B$13=0, Q13<=0, Q13<INPUTS!$B$13) | S13: =OR(I13,K13,N13,R13) | T13: =OR(I13,L13,O13,R13)
... A10626: 300 | B10626: 300 | C10626: 200 | D10626: =(A10626+B10626)/2 + C10626/2 | E10626: =SQRT(A10626^2+B10626^2+C10626^2) | F10626: =INPUTS!$B$8*A10626+INPUTS!$B$9*D10626+INPUTS!$B$10*B10626 | G10626: =INPUTS!$B$11*A10626/10000 | H10626: =MAX(0, (INPUTS!$B$14+INPUTS!$B$16*INPUTS!$B$15) + (1-INPUTS!$B$18)*INPUTS!$B$19*G10626 - INPUTS!$B$17 - INPUTS!$B$20*MAX(0, -F10626)) | I10626: =IF(INPUTS!$B$13=0, H10626<=0, H10626<INPUTS!$B$13) | J10626: =INPUTS!$B$21 + INPUTS!$B$24*F10626 + INPUTS!$B$25*G10626 | K10626: =J10626<INPUTS!$B$23 | L10626: =J10626<INPUTS!$B$22 | M10626: =INPUTS!$B$26 + INPUTS!$B$29*F10626 | N10626: =M10626<INPUTS!$B$28 | O10626: =M10626<INPUTS!$B$27 | P10626: =INPUTS!$B$30 + (1-INPUTS!$B$18)*INPUTS!$B$19*G10626 | Q10626: =INPUTS!$B$31 + INPUTS!$B$32*P10626 | R10626: =IF(INPUTS!$B$13=0, Q10626<=0, Q10626<INPUTS!$B$13) | S10626: =OR(I10626,K10626,N10626,R10626) | T10626: =OR(I10626,L10626,O10626,R10626)

Sheet OPTIMUM
A1: item | B1: value | C1: formula / explanation
A2: min_theta_bp (NoDividend_floor=TRUE) | B2: =MIN(IF(FRONTIER_POINTS!$T$2:$T$10626,FRONTIER_POINTS!$E$2:$E$10626)) | C2: =MIN(IF(FRONTIER_POINTS!$T$2:$T$10626,FRONTIER_POINTS!$E$2:$E$10626))
A3: best_dr_short_bp | B3: =INDEX(FRONTIER_POINTS!$A$2:$A$10626, MATCH(B2, FRONTIER_POINTS!$E$2:$E$10626, 0)) | C3: =INDEX(FRONTIER_POINTS!$A$2:$A$10626, MATCH(B2, FRONTIER_POINTS!$E$2:$E$10626, 0))
A4: best_dr_long_bp | B4: =INDEX(FRONTIER_POINTS!$B$2:$B$10626, MATCH(B2, FRONTIER_POINTS!$E$2:$E$10626, 0)) | C4: =INDEX(FRONTIER_POINTS!$B$2:$B$10626, MATCH(B2, FRONTIER_POINTS!$E$2:$E$10626, 0))
A5: best_curv_bp | B5: =INDEX(FRONTIER_POINTS!$C$2:$C$10626, MATCH(B2, FRONTIER_POINTS!$E$2:$E$10626, 0)) | C5: =INDEX(FRONTIER_POINTS!$C$2:$C$10626, MATCH(B2, FRONTIER_POINTS!$E$2:$E$10626, 0))
A6: best_dr_mid_bp | B6: =INDEX(FRONTIER_POINTS!$D$2:$D$10626, MATCH(B2, FRONTIER_POINTS!$E$2:$E$10626, 0)) | C6: =INDEX(FRONTIER_POINTS!$D$2:$D$10626, MATCH(B2, FRONTIER_POINTS!$E$2:$E$10626, 0))
A7: ΔEVE_mEUR @ optimum | B7: =INDEX(FRONTIER_POINTS!$F$2:$F$10626, MATCH(B2, FRONTIER_POINTS!$E$2:$E$10626, 0)) | C7: =INDEX(FRONTIER_POINTS!$F$2:$F$10626, MATCH(B2, FRONTIER_POINTS!$E$2:$E$10626, 0))
A8: ΔNII_12m_mEUR @ optimum | B8: =INDEX(FRONTIER_POINTS!$G$2:$G$10626, MATCH(B2, FRONTIER_POINTS!$E$2:$E$10626, 0)) | C8: =INDEX(FRONTIER_POINTS!$G$2:$G$10626, MATCH(B2, FRONTIER_POINTS!$E$2:$E$10626, 0))
A9: branch causing NoDividend_floor | C9: See FRONTIER_POINTS flags at the optimum row (Cash/CET1/SII/Legal).

Sheet NOTES
A1: Deterministic Reverse Stress Test (RST) – built from 2024 consolidated balance-sheet sensitivity table (flag 'Y' = interest-rate sensitive).
A3: Key modelling choices (sensitivity-only):
A4: 1) ΔEVE is computed from bucket PV01 allocations calibrated to match the observed net ΔEVE for a +100bp shock in the sensitivity table:
A5: ΔEVE(+100bp) observed = -24,443.4 mEUR (Assets Δ - Liabilities Δ).
A6: We allocate PV01 across 3 maturity buckets (<1y, 1–5y, >5y) using duration midpoints (0.5, 3, 10) and scale all bucket PV01s by k so that the parallel shock matches the observed ΔEVE.
A7: 2) Curve parameterisation uses (short, long, curvature) with mid shock derived as: mid = (short+long)/2 + curv/2.
A8: 3) ΔNII(12m) uses repricing gap proxy: ΔNII = GAP_<1y * short_bp / 10000, where GAP_<1y = Net(<1y) from the same sensitivity table (interest-rate sensitive only).
A9: 4) Fail-state uses 4 branches with OR logic (Cash / CET1 / SII / Legal) and both floor vs target thresholds (inputs).
A10: - CET1 baseline and SREP floor are sourced from DEU 'Ratios prudentiels' chart (LBP).
A11: - SII and Legal thresholds are left as inputs to be replaced by DEU/SFCR or internal governance data if not disclosed at group level.
A13: Important limitation:
A14: This file intentionally does NOT bucketise insurance liabilities alone (IFRS17) beyond what is already embedded in the 'Y' sensitivity deltas; any separate insurance module should be modelled with assets backing / SII proxy to avoid double-counting.
... A17: Adjust editable inputs in INPUTS (blue cells) and review OPTIMUM for the minimum-theta shock that triggers NoDividend (floor rule).
